[
  {
    "Username": "Rhoda",
    "Email": "rhodajuarez@firewax.com",
    "Gender": "female",
    "DateOfBirth": "1974-11-28",
    "Password": "123#Aa",
    "Created": "2018-11-30",
    "Bio": "Mollit ea irure deserunt esse dolore ad eu ut minim commodo. Proident tempor ullamco labore commodo laborum tempor anim consectetur sint. Ea duis incididunt ad est cillum et. Duis incididunt tempor consectetur exercitation nisi ipsum nisi cillum tempor laboris ipsum. Nostrud ullamco aute eu deserunt cupidatat mollit proident adipisicing esse adipisicing ea nisi dolor.\r\n",
    "Interests": "Ullamco nostrud ea sunt sit velit excepteur nulla mollit.",
    "City": "Bentonville",
    "Country": "Slovenia",
    "Products": [
      {
        "Name": "Product 29",
        "Price": 26,
        "Phone": "+1 (870) 576-3453",
        "Address": "227 Hamilton Walk, Rockhill, Louisiana, 6970",
        "Email": "rhodajuarez@firewax.com",
        "DateAdded": "2018-06-24",
        "description": "Et aliquip occaecat exercitation ex ipsum velit dolore ad aliqua.",
        "Photos": [
          {
            "url": "https://www.randomlists.com/img/things/controller.webp",
            "isMain": true,
            "description": "Ut amet id amet nisi consequat in."
          }
        ]
      }
    ]
  },
  {
    "Username": "Megan",
    "Email": "meganjuarez@firewax.com",
    "Gender": "female",
    "DateOfBirth": "1975-07-31",
    "Password": "123#Aa",
    "Created": "2018-08-15",
    "Bio": "Occaecat pariatur ad pariatur exercitation. Sint laborum nisi sunt aliqua officia ad velit ullamco ea cupidatat laborum minim ad culpa. Consequat eu laboris est duis id. Dolor magna id sint incididunt esse ex occaecat aliquip sint velit laborum.\r\n",
    "Interests": "Quis proident cillum aliquip aliquip veniam cupidatat duis ullamco mollit minim.",
    "City": "Wakarusa",
    "Country": "Saint Lucia",
    "Products": [
      {
        "Name": "Product 28",
        "Price": 22,
        "Phone": "+1 (862) 525-2627",
        "Address": "824 Moultrie Street, Oneida, New Mexico, 1549",
        "Email": "meganjuarez@firewax.com",
        "DateAdded": "2018-03-06",
        "description": "Anim occaecat aute voluptate irure sit aliqua sunt qui.",
        "Photos": [
          {
            "url": "https://www.randomlists.com/img/things/controller.webp",
            "isMain": true,
            "description": "Irure laboris est do pariatur velit velit amet ipsum ea."
          }
        ]
      }
    ]
  },
  {
    "Username": "Audrey",
    "Email": "audreyjuarez@firewax.com",
    "Gender": "female",
    "DateOfBirth": "1978-12-15",
    "Password": "123#Aa",
    "Created": "2018-09-01",
    "Bio": "Ex ut esse esse do ea. Do deserunt culpa Lorem nisi sit aliquip non ex consectetur duis voluptate elit. Dolore veniam sint esse eiusmod voluptate nostrud minim. Cupidatat cillum exercitation aliqua ex pariatur consequat cillum voluptate. Ut quis nisi proident nisi aliquip laboris nulla nulla. Dolore dolore culpa excepteur minim.\r\n",
    "Interests": "Fugiat officia laborum esse in do.",
    "City": "Why",
    "Country": "Burkina Faso",
    "Products": [
      {
        "Name": "Product 19",
        "Price": 21,
        "Phone": "+1 (829) 469-2581",
        "Address": "301 Lynch Street, Zortman, Washington, 6719",
        "Email": "audreyjuarez@firewax.com",
        "DateAdded": "2018-11-04",
        "description": "Minim nisi esse ullamco tempor ullamco fugiat ipsum enim reprehenderit non.",
        "Photos": [
          {
            "url": "https://www.randomlists.com/img/things/controller.webp",
            "isMain": true,
            "description": "Consequat sunt voluptate excepteur do ipsum fugiat reprehenderit nulla nisi occaecat ullamco ipsum in."
          }
        ]
      }
    ]
  },
  {
    "Username": "Vickie",
    "Email": "vickiejuarez@firewax.com",
    "Gender": "female",
    "DateOfBirth": "1992-01-19",
    "Password": "123#Aa",
    "Created": "2018-11-06",
    "Bio": "Elit commodo sit dolor do dolore velit et consectetur. Veniam irure irure ea fugiat non consequat nulla anim magna non. Ad ullamco nulla qui occaecat tempor consequat incididunt nostrud sit esse excepteur. Nisi incididunt qui consectetur laborum nostrud. Dolore anim minim aliquip elit occaecat dolore voluptate amet tempor proident duis officia ullamco. Sit ex aute ullamco exercitation.\r\n",
    "Interests": "Ullamco esse pariatur incididunt elit adipisicing mollit eu sint culpa est tempor aliqua elit.",
    "City": "Accoville",
    "Country": "Ecuador",
    "Products": [
      {
        "Name": "Product 19",
        "Price": 29,
        "Phone": "+1 (974) 588-2358",
        "Address": "367 Jamaica Avenue, Allentown, Massachusetts, 3914",
        "Email": "vickiejuarez@firewax.com",
        "DateAdded": "2018-09-29",
        "description": "Proident occaecat tempor amet minim magna Lorem veniam adipisicing qui laboris.",
        "Photos": [
          {
            "url": "https://www.randomlists.com/img/things/controller.webp",
            "isMain": true,
            "description": "Eiusmod sint reprehenderit laborum tempor sit ad ad ex deserunt consequat."
          }
        ]
      }
    ]
  },
  {
    "Username": "Lynda",
    "Email": "lyndajuarez@firewax.com",
    "Gender": "female",
    "DateOfBirth": "1987-02-24",
    "Password": "123#Aa",
    "Created": "2018-02-22",
    "Bio": "Incididunt et eu exercitation mollit et ea sunt sunt fugiat dolor occaecat sit nisi. Officia fugiat incididunt ea qui dolore. Eiusmod in esse irure id esse.\r\n",
    "Interests": "Excepteur aliquip dolore ullamco exercitation laborum consectetur eiusmod anim magna consectetur minim nulla.",
    "City": "Konterra",
    "Country": "Northern Mariana Islands",
    "Products": [
      {
        "Name": "Product 18",
        "Price": 31,
        "Phone": "+1 (809) 558-2601",
        "Address": "233 Navy Walk, Leola, Vermont, 8535",
        "Email": "lyndajuarez@firewax.com",
        "DateAdded": "2018-12-28",
        "description": "Cupidatat excepteur occaecat eu reprehenderit fugiat tempor id.",
        "Photos": [
          {
            "url": "https://www.randomlists.com/img/things/controller.webp",
            "isMain": true,
            "description": "Consectetur dolor esse do commodo."
          }
        ]
      }
    ]
  },
  {
    "Username": "Marjorie",
    "Email": "marjoriejuarez@firewax.com",
    "Gender": "female",
    "DateOfBirth": "1981-08-20",
    "Password": "123#Aa",
    "Created": "2018-12-29",
    "Bio": "Cupidatat culpa amet aliqua est ipsum. Esse laborum minim pariatur exercitation ipsum officia exercitation enim pariatur do. Aliquip proident cillum magna do veniam.\r\n",
    "Interests": "Ex aliquip exercitation excepteur qui ea.",
    "City": "Grill",
    "Country": "Nepal",
    "Products": [
      {
        "Name": "Product 39",
        "Price": 25,
        "Phone": "+1 (913) 444-3305",
        "Address": "612 Bayview Avenue, Gulf, New Jersey, 5559",
        "Email": "marjoriejuarez@firewax.com",
        "DateAdded": "2018-07-09",
        "description": "Amet consequat irure adipisicing excepteur duis esse consectetur aute minim ad ut aliqua velit proident.",
        "Photos": [
          {
            "url": "https://www.randomlists.com/img/things/controller.webp",
            "isMain": true,
            "description": "Sunt nostrud culpa dolore et."
          }
        ]
      }
    ]
  },
  {
    "Username": "Heidi",
    "Email": "heidijuarez@firewax.com",
    "Gender": "female",
    "DateOfBirth": "1996-12-27",
    "Password": "123#Aa",
    "Created": "2018-04-12",
    "Bio": "Laboris exercitation Lorem sit labore deserunt exercitation enim voluptate commodo esse ex sint. Laboris ullamco dolore exercitation aute Lorem sit. Reprehenderit excepteur occaecat exercitation laborum mollit ea amet ex velit velit. Nisi laborum et velit consequat exercitation ex labore ea tempor magna est nulla duis et. Proident laborum proident id dolore. Magna sit ea laboris nisi dolor fugiat dolor ullamco sint anim exercitation ad non reprehenderit.\r\n",
    "Interests": "Duis laborum ipsum labore qui consectetur proident id dolore sint aute.",
    "City": "Joppa",
    "Country": "Nauru",
    "Products": [
      {
        "Name": "Product 1",
        "Price": 20,
        "Phone": "+1 (811) 597-2693",
        "Address": "418 Ryder Street, Dana, Marshall Islands, 3637",
        "Email": "heidijuarez@firewax.com",
        "DateAdded": "2018-12-16",
        "description": "Irure cupidatat anim aliquip consectetur dolor ex.",
        "Photos": [
          {
            "url": "https://www.randomlists.com/img/things/controller.webp",
            "isMain": true,
            "description": "Officia laborum in laboris reprehenderit veniam id nulla eu aliqua aute."
          }
        ]
      }
    ]
  },
  {
    "Username": "Tamera",
    "Email": "tamerajuarez@firewax.com",
    "Gender": "female",
    "DateOfBirth": "1994-05-06",
    "Password": "123#Aa",
    "Created": "2018-08-17",
    "Bio": "Eu nulla consectetur laborum ipsum minim esse occaecat duis cupidatat et ad qui. Qui consectetur amet non ullamco ea consectetur nulla nulla pariatur Lorem ullamco aliqua ea. Velit sunt anim laboris est ullamco velit mollit aliqua qui in. Est consequat ullamco ipsum adipisicing ut sit amet do et mollit do. Eu eu labore eiusmod incididunt deserunt incididunt dolor eu ut sint tempor. Ipsum officia commodo enim eiusmod officia sint consequat in esse occaecat.\r\n",
    "Interests": "Fugiat do sunt Lorem id velit aliquip ex enim nostrud Lorem amet.",
    "City": "Hanover",
    "Country": "Romania",
    "Products": [
      {
        "Name": "Product 2",
        "Price": 24,
        "Phone": "+1 (958) 599-2903",
        "Address": "804 Randolph Street, Draper, Arizona, 5135",
        "Email": "tamerajuarez@firewax.com",
        "DateAdded": "2019-01-14",
        "description": "Ullamco qui labore nisi cillum exercitation adipisicing ullamco qui.",
        "Photos": [
          {
            "url": "https://www.randomlists.com/img/things/controller.webp",
            "isMain": true,
            "description": "Ad sunt id qui mollit ad elit."
          }
        ]
      }
    ]
  },
  {
    "Username": "Jeannine",
    "Email": "jeanninejuarez@firewax.com",
    "Gender": "female",
    "DateOfBirth": "1978-09-11",
    "Password": "123#Aa",
    "Created": "2018-10-01",
    "Bio": "Irure anim ad qui reprehenderit consequat qui duis. Nulla ad cupidatat mollit qui consequat aliqua cupidatat ullamco dolor fugiat ut. Labore deserunt proident adipisicing sint voluptate incididunt cupidatat irure. Quis ut incididunt laboris aliqua adipisicing ex nisi. Culpa incididunt ex incididunt dolore exercitation amet ex eu non amet sunt consequat.\r\n",
    "Interests": "Enim exercitation voluptate proident anim ipsum aute quis.",
    "City": "Fingerville",
    "Country": "Bhutan",
    "Products": [
      {
        "Name": "Product 4",
        "Price": 21,
        "Phone": "+1 (999) 527-2211",
        "Address": "809 Nixon Court, Bradenville, Nevada, 9096",
        "Email": "jeanninejuarez@firewax.com",
        "DateAdded": "2018-08-29",
        "description": "Sunt eu proident mollit elit cillum et duis.",
        "Photos": [
          {
            "url": "https://www.randomlists.com/img/things/controller.webp",
            "isMain": true,
            "description": "Enim amet irure velit elit."
          }
        ]
      }
    ]
  },
  {
    "Username": "Cathryn",
    "Email": "cathrynjuarez@firewax.com",
    "Gender": "female",
    "DateOfBirth": "1987-10-11",
    "Password": "123#Aa",
    "Created": "2018-09-16",
    "Bio": "Ad enim cupidatat duis ea labore irure eu nisi eu culpa ut veniam ad eu. Duis commodo nisi laborum veniam pariatur velit ex. Id incididunt tempor magna commodo aliquip eiusmod ut. Id sint fugiat ex dolor qui incididunt. Eiusmod in do excepteur Lorem velit eu. Laborum commodo veniam incididunt nostrud. Velit labore irure irure mollit nisi laboris ipsum cillum dolor veniam excepteur.\r\n",
    "Interests": "Ullamco ex deserunt exercitation est Lorem nostrud cupidatat nulla sit.",
    "City": "Salvo",
    "Country": "Gibraltar",
    "Products": [
      {
        "Name": "Product 14",
        "Price": 30,
        "Phone": "+1 (880) 403-3028",
        "Address": "346 Fair Street, Rosine, Ohio, 8389",
        "Email": "cathrynjuarez@firewax.com",
        "DateAdded": "2018-07-03",
        "description": "Sit veniam velit aliqua pariatur nulla.",
        "Photos": [
          {
            "url": "https://www.randomlists.com/img/things/controller.webp",
            "isMain": true,
            "description": "Ea ad deserunt qui ullamco enim pariatur ut consequat."
          }
        ]
      }
    ]
  },
  {
    "Username": "Kathryn",
    "Email": "kathrynjuarez@firewax.com",
    "Gender": "female",
    "DateOfBirth": "1997-02-24",
    "Password": "123#Aa",
    "Created": "2018-09-14",
    "Bio": "Adipisicing sunt consequat ex veniam eiusmod sint occaecat nulla amet tempor cillum. Dolor consectetur excepteur velit excepteur esse enim laborum aute eiusmod qui minim eu mollit. Exercitation aute adipisicing amet laboris incididunt ut ea occaecat et ullamco reprehenderit veniam ipsum consequat. Sint aliquip veniam minim elit commodo.\r\n",
    "Interests": "Aliquip do dolore veniam elit duis.",
    "City": "Biddle",
    "Country": "Dominica",
    "Products": [
      {
        "Name": "Product 40",
        "Price": 28,
        "Phone": "+1 (966) 564-2162",
        "Address": "283 Columbia Place, Wawona, New Hampshire, 9971",
        "Email": "kathrynjuarez@firewax.com",
        "DateAdded": "2018-11-09",
        "description": "Eu eu minim qui exercitation reprehenderit exercitation excepteur tempor ullamco eiusmod elit consectetur.",
        "Photos": [
          {
            "url": "https://www.randomlists.com/img/things/controller.webp",
            "isMain": true,
            "description": "Ullamco incididunt sit in tempor velit."
          }
        ]
      }
    ]
  },
  {
    "Username": "Lynne",
    "Email": "lynnejuarez@firewax.com",
    "Gender": "female",
    "DateOfBirth": "1998-09-17",
    "Password": "123#Aa",
    "Created": "2018-10-28",
    "Bio": "Nisi ipsum anim mollit velit voluptate eu velit. Ullamco esse ullamco nostrud aute veniam labore labore nisi anim. Eiusmod irure nostrud cupidatat ea veniam sit fugiat eiusmod enim officia non. Magna sit Lorem reprehenderit nostrud mollit anim exercitation quis.\r\n",
    "Interests": "Irure eiusmod velit cupidatat pariatur et velit.",
    "City": "Brewster",
    "Country": "Uganda",
    "Products": [
      {
        "Name": "Product 20",
        "Price": 22,
        "Phone": "+1 (812) 432-3317",
        "Address": "766 Noel Avenue, Frystown, Alaska, 2125",
        "Email": "lynnejuarez@firewax.com",
        "DateAdded": "2018-12-06",
        "description": "Nulla laborum do tempor occaecat.",
        "Photos": [
          {
            "url": "https://www.randomlists.com/img/things/controller.webp",
            "isMain": true,
            "description": "Excepteur excepteur tempor magna cupidatat."
          }
        ]
      }
    ]
  },
  {
    "Username": "Velma",
    "Email": "velmajuarez@firewax.com",
    "Gender": "female",
    "DateOfBirth": "1984-06-08",
    "Password": "123#Aa",
    "Created": "2018-06-01",
    "Bio": "Non fugiat incididunt ut ipsum aliqua veniam proident. Dolore incididunt elit eu dolor elit aliqua est elit eu veniam tempor. Ea Lorem excepteur qui proident aliqua aute ad ad labore laborum id deserunt. Nulla occaecat sunt deserunt non magna. Quis reprehenderit aliqua ad culpa ullamco ipsum Lorem nulla amet tempor consectetur excepteur.\r\n",
    "Interests": "Elit voluptate duis ex labore.",
    "City": "Hendersonville",
    "Country": "Thailand",
    "Products": [
      {
        "Name": "Product 26",
        "Price": 23,
        "Phone": "+1 (979) 411-3740",
        "Address": "446 Maple Street, Volta, Mississippi, 2566",
        "Email": "velmajuarez@firewax.com",
        "DateAdded": "2018-04-11",
        "description": "Irure in excepteur id fugiat qui quis ex veniam.",
        "Photos": [
          {
            "url": "https://www.randomlists.com/img/things/controller.webp",
            "isMain": true,
            "description": "In anim sunt qui elit duis non labore."
          }
        ]
      }
    ]
  },
  {
    "Username": "Sheryl",
    "Email": "sheryljuarez@firewax.com",
    "Gender": "female",
    "DateOfBirth": "1996-01-16",
    "Password": "123#Aa",
    "Created": "2018-10-01",
    "Bio": "Ut aute reprehenderit aliquip ullamco. Ullamco ex id ipsum nulla ea eiusmod consequat exercitation enim deserunt ipsum labore nostrud. In laborum aliquip voluptate eiusmod commodo ea sint consequat ea qui occaecat veniam nulla. Esse nulla id incididunt occaecat enim elit laboris consectetur proident esse. Labore sunt duis exercitation ullamco dolore ut eiusmod velit tempor in est.\r\n",
    "Interests": "Culpa proident est occaecat ut enim laborum exercitation excepteur commodo ullamco voluptate do proident voluptate.",
    "City": "Riceville",
    "Country": "Wallis and Futuna Islands",
    "Products": [
      {
        "Name": "Product 34",
        "Price": 22,
        "Phone": "+1 (864) 508-2983",
        "Address": "927 Tech Place, Brecon, Minnesota, 5409",
        "Email": "sheryljuarez@firewax.com",
        "DateAdded": "2019-01-12",
        "description": "Est ex commodo adipisicing consequat et nisi in incididunt adipisicing.",
        "Photos": [
          {
            "url": "https://www.randomlists.com/img/things/controller.webp",
            "isMain": true,
            "description": "Pariatur minim proident nisi aliqua ad et officia ad dolor tempor nulla."
          }
        ]
      }
    ]
  },
  {
    "Username": "Mayra",
    "Email": "mayrajuarez@firewax.com",
    "Gender": "female",
    "DateOfBirth": "1990-12-19",
    "Password": "123#Aa",
    "Created": "2018-08-14",
    "Bio": "Esse deserunt adipisicing enim tempor ea laborum laborum nostrud tempor eiusmod do aliquip est cupidatat. Non Lorem amet veniam incididunt consequat elit officia labore duis est cupidatat excepteur id elit. Do adipisicing sunt cupidatat est adipisicing ullamco ad irure quis. Velit ipsum esse pariatur culpa laborum ullamco deserunt occaecat aute commodo enim laboris.\r\n",
    "Interests": "Aliqua do elit consectetur excepteur magna laborum.",
    "City": "Callaghan",
    "Country": "Antarctica",
    "Products": [
      {
        "Name": "Product 14",
        "Price": 34,
        "Phone": "+1 (957) 483-3696",
        "Address": "675 Prospect Place, Canby, Utah, 5175",
        "Email": "mayrajuarez@firewax.com",
        "DateAdded": "2018-11-14",
        "description": "Reprehenderit excepteur aute incididunt excepteur reprehenderit do dolor adipisicing culpa.",
        "Photos": [
          {
            "url": "https://www.randomlists.com/img/things/controller.webp",
            "isMain": true,
            "description": "Eiusmod proident ea do ea ad nostrud cillum enim laboris aliqua voluptate qui labore eiusmod."
          }
        ]
      }
    ]
  },
  {
    "Username": "Pauline",
    "Email": "paulinejuarez@firewax.com",
    "Gender": "female",
    "DateOfBirth": "1993-12-11",
    "Password": "123#Aa",
    "Created": "2018-05-31",
    "Bio": "Velit incididunt adipisicing anim pariatur culpa culpa sit consectetur duis dolore excepteur. Amet irure excepteur nostrud enim laboris in cillum adipisicing ut eiusmod pariatur in ad. Ut ad magna amet excepteur Lorem duis ad labore magna do pariatur aliqua.\r\n",
    "Interests": "Nulla ea nulla eiusmod enim magna magna magna.",
    "City": "Edgar",
    "Country": "Libya",
    "Products": [
      {
        "Name": "Product 25",
        "Price": 29,
        "Phone": "+1 (801) 433-2446",
        "Address": "993 Church Avenue, Swartzville, Idaho, 3444",
        "Email": "paulinejuarez@firewax.com",
        "DateAdded": "2018-05-16",
        "description": "Reprehenderit amet fugiat cillum est.",
        "Photos": [
          {
            "url": "https://www.randomlists.com/img/things/controller.webp",
            "isMain": true,
            "description": "Aliquip esse culpa cillum proident ad velit culpa amet deserunt ex in ut."
          }
        ]
      }
    ]
  },
  {
    "Username": "Katie",
    "Email": "katiejuarez@firewax.com",
    "Gender": "female",
    "DateOfBirth": "1982-01-24",
    "Password": "123#Aa",
    "Created": "2018-06-13",
    "Bio": "Magna duis et ut proident irure eiusmod ea dolor duis ea. Do magna qui aute quis nisi voluptate ea excepteur eu mollit ipsum. Excepteur esse qui nostrud laborum culpa officia id labore consequat non cillum. Et incididunt aute aliquip irure irure mollit commodo esse ipsum pariatur officia voluptate nisi.\r\n",
    "Interests": "Labore aute ea aliqua mollit occaecat.",
    "City": "Chemung",
    "Country": "Gabon",
    "Products": [
      {
        "Name": "Product 8",
        "Price": 33,
        "Phone": "+1 (953) 532-3530",
        "Address": "937 Tiffany Place, Waumandee, Virginia, 4532",
        "Email": "katiejuarez@firewax.com",
        "DateAdded": "2018-01-01",
        "description": "Ea eiusmod qui elit nostrud magna voluptate mollit esse voluptate veniam.",
        "Photos": [
          {
            "url": "https://www.randomlists.com/img/things/controller.webp",
            "isMain": true,
            "description": "Labore duis consectetur aliqua ullamco sit id excepteur culpa."
          }
        ]
      }
    ]
  },
  {
    "Username": "Eunice",
    "Email": "eunicejuarez@firewax.com",
    "Gender": "female",
    "DateOfBirth": "1986-12-08",
    "Password": "123#Aa",
    "Created": "2019-01-08",
    "Bio": "Aliquip ad ex sit quis aliquip qui cillum laborum ullamco aute anim id. Velit ut fugiat sint enim. Excepteur consequat aute ad culpa nostrud aliqua minim eiusmod. Consequat in do elit fugiat incididunt labore amet aliqua.\r\n",
    "Interests": "Id qui excepteur tempor excepteur minim ad.",
    "City": "Waikele",
    "Country": "Bangladesh",
    "Products": [
      {
        "Name": "Product 17",
        "Price": 34,
        "Phone": "+1 (858) 582-2646",
        "Address": "615 Moore Place, Eagletown, West Virginia, 8912",
        "Email": "eunicejuarez@firewax.com",
        "DateAdded": "2018-12-03",
        "description": "Quis duis esse do ipsum ad.",
        "Photos": [
          {
            "url": "https://www.randomlists.com/img/things/controller.webp",
            "isMain": true,
            "description": "Laboris occaecat do ipsum Lorem adipisicing veniam nisi."
          }
        ]
      }
    ]
  },
  {
    "Username": "Lee",
    "Email": "leejuarez@firewax.com",
    "Gender": "female",
    "DateOfBirth": "1971-04-23",
    "Password": "123#Aa",
    "Created": "2018-04-15",
    "Bio": "Magna do qui eu ullamco consequat nisi irure eiusmod consectetur adipisicing. Ut consectetur elit veniam nostrud id ipsum sit ad sint sunt ex irure. Fugiat est do duis anim duis ullamco culpa est voluptate labore. Non id commodo ipsum sit est minim ipsum commodo id aliquip. Velit est cillum ullamco id ad nulla sit id minim culpa.\r\n",
    "Interests": "Consectetur fugiat sint eiusmod sint consequat sunt in.",
    "City": "Osmond",
    "Country": "Zaire",
    "Products": [
      {
        "Name": "Product 7",
        "Price": 39,
        "Phone": "+1 (929) 424-2772",
        "Address": "439 Clark Street, Lindcove, Alabama, 1049",
        "Email": "leejuarez@firewax.com",
        "DateAdded": "2018-08-16",
        "description": "Commodo laborum sit sint et reprehenderit id in adipisicing.",
        "Photos": [
          {
            "url": "https://www.randomlists.com/img/things/controller.webp",
            "isMain": true,
            "description": "Laborum labore et enim fugiat adipisicing quis dolor adipisicing sunt."
          }
        ]
      }
    ]
  },
  {
    "Username": "Aileen",
    "Email": "aileenjuarez@firewax.com",
    "Gender": "female",
    "DateOfBirth": "1998-06-02",
    "Password": "123#Aa",
    "Created": "2018-05-14",
    "Bio": "Eu anim qui excepteur ex cupidatat adipisicing excepteur occaecat. Consequat laboris laboris irure sunt. Consequat velit esse adipisicing adipisicing elit nostrud anim incididunt. Commodo nulla esse est Lorem proident sint ut ad tempor do dolor eu ullamco.\r\n",
    "Interests": "Fugiat irure ipsum aliquip et quis quis irure tempor.",
    "City": "Graball",
    "Country": "Russian Federation",
    "Products": [
      {
        "Name": "Product 5",
        "Price": 33,
        "Phone": "+1 (891) 456-3463",
        "Address": "331 Ashford Street, Sunbury, Maryland, 2865",
        "Email": "aileenjuarez@firewax.com",
        "DateAdded": "2018-12-18",
        "description": "Laborum fugiat commodo nulla mollit velit id.",
        "Photos": [
          {
            "url": "https://www.randomlists.com/img/things/controller.webp",
            "isMain": true,
            "description": "Consectetur sit est incididunt dolore occaecat aute tempor."
          }
        ]
      }
    ]
  }
]